odoo10_addon_stay_report_py3o-10.0.1.0.0-py2.7-nspkg.pth
odoo/addons/stay_report_py3o/README.rst
odoo/addons/stay_report_py3o/__init__.py
odoo/addons/stay_report_py3o/__manifest__.py
odoo/addons/stay_report_py3o/report.xml
odoo/addons/stay_report_py3o/stay_journal.odt
odoo10_addon_stay_report_py3o-10.0.1.0.0.dist-info/DESCRIPTION.rst
odoo10_addon_stay_report_py3o-10.0.1.0.0.dist-info/METADATA
odoo10_addon_stay_report_py3o-10.0.1.0.0.dist-info/RECORD
odoo10_addon_stay_report_py3o-10.0.1.0.0.dist-info/WHEEL
odoo10_addon_stay_report_py3o-10.0.1.0.0.dist-info/metadata.json
odoo10_addon_stay_report_py3o-10.0.1.0.0.dist-info/namespace_packages.txt
odoo10_addon_stay_report_py3o-10.0.1.0.0.dist-info/top_level.txt
